README
setup.py
cli_query/__init__.py
cli_query/management/__init__.py
cli_query/management/commands/__init__.py
cli_query/management/commands/query.py
django_cli_query.egg-info/PKG-INFO
django_cli_query.egg-info/SOURCES.txt
django_cli_query.egg-info/dependency_links.txt
django_cli_query.egg-info/top_level.txt