Metadata-Version: 1.1
Name: django-cli-query
Version: 1.0
Summary: Management command for commandline querying
Home-page: http://github.com/seveas/django-cli-query
Author: Dennis Kaarsemaker
Author-email: dennis@kaarsemaker.net
License: UNKNOWN
Platform: UNKNOWN
Classifier: Development Status :: 5 - Production/Stable
Classifier: Framework :: Django
Classifier: Intended Audience :: Developers
Classifier: Operating System :: OS Independent
Classifier: Topic :: Software Development
